pysimlink/__init__.py
pysimlink/c_files/include/containers.hpp
pysimlink/c_files/include/dev_tools.hpp
pysimlink/c_files/include/model_interface.hpp
pysimlink/c_files/include/model_interface.tpp
pysimlink/c_files/include/model_utils.hpp
pysimlink/c_files/include/model_utils.tpp
pysimlink/c_files/include/safe_utils.hpp
pysimlink/c_files/src/bindings.cpp
pysimlink/c_files/src/dev_tools.cpp
pysimlink/c_files/src/hash.cpp
pysimlink/c_files/src/model_interface.cpp
pysimlink/c_files/src/model_utils.cpp
pysimlink/c_files/src/safe_utils.cpp
pysimlink/lib/__init__.py
pysimlink/lib/cmake_gen.py
pysimlink/lib/dependency_graph.py
pysimlink/lib/exceptions.py
pysimlink/lib/model.py
pysimlink/lib/model_paths.py
pysimlink/lib/model_types.py
pysimlink/lib/spinner.py
pysimlink/lib/struct_parser.py
pysimlink/lib/compilers/__init__.py
pysimlink/lib/compilers/compiler.py
pysimlink/lib/compilers/model_ref_compiler.py
pysimlink/lib/compilers/one_shot_compiler.py
pysimlink/utils/__init__.py
pysimlink/utils/annotation_utils.py
pysimlink/utils/model_utils.py
pysimlink-1.2.1.dist-info/LICENSE.txt
pysimlink-1.2.1.dist-info/METADATA
pysimlink-1.2.1.dist-info/WHEEL
pysimlink-1.2.1.dist-info/top_level.txt
pysimlink-1.2.1.dist-info/RECORD
