Metadata-Version: 2.1
Name: pysimlink
Version: 1.2.1
Summary: Compile, run, and interact with Simulink models natively in Python!
Home-page: https://github.com/lharri73/PySimlink
Author: Landon Harris
Author-email: lharri73@vols.utk.edu
License: GPLv3
Project-URL: Documentation, https://lharri73.github.io/PySimlink/
Project-URL: Source, https://github.com/lharri73/PySimlink
Keywords: Simulink
Classifier: Topic :: Scientific/Engineering
Classifier: Topic :: Software Development :: Code Generators
Classifier: Programming Language :: Python :: 3
Classifier: Development Status :: 3 - Alpha
Classifier: License :: OSI Approved :: GNU General Public License v3 (GPLv3)
Classifier: Operating System :: MacOS :: MacOS X
Classifier: Operating System :: POSIX
Requires-Python: >=3.6
License-File: LICENSE.txt
Requires-Dist: cmake
Requires-Dist: numpy
Requires-Dist: pybind11
Provides-Extra: dev
Requires-Dist: pylint ; extra == 'dev'
Requires-Dist: black ; extra == 'dev'
Requires-Dist: sphinx-rtd-theme ; extra == 'dev'
Requires-Dist: sphinx ; extra == 'dev'
Requires-Dist: tqdm ; extra == 'dev'
Requires-Dist: sphinx-toolbox ; extra == 'dev'
Requires-Dist: sphinx-hoverxref ; extra == 'dev'
Requires-Dist: readthedocs-sphinx-search ; extra == 'dev'
